propkatraj/__init__.py
propkatraj/propkatraj.py
propkatraj/tests/__init__.py
propkatraj/tests/datafiles.py
propkatraj/tests/test_import.py
propkatraj/tests/test_regression.py
propkatraj/tests/data/__init__.py
propkatraj/tests/data/atterr_frame1.pdb
propkatraj/tests/data/atterr_frame1.xtc
propkatraj/tests/data/indexerr_frame14.gro
propkatraj/tests/data/indexerr_frame14.xtc
propkatraj/tests/data/psf_ref_frame0.pka
propkatraj/tests/data/psf_ref_frame90.pka
propkatraj-2.0.1.dist-info/LICENSE
propkatraj-2.0.1.dist-info/METADATA
propkatraj-2.0.1.dist-info/WHEEL
propkatraj-2.0.1.dist-info/top_level.txt
propkatraj-2.0.1.dist-info/RECORD
