Metadata-Version: 2.1
Name: propkatraj
Version: 2.0.1
Summary: Obtain pKas for titreatable residues from a simulation trajectory.
Author: propkatraj AUTHORS
Author-email: David Dotson <dotsdl@gmail.com>, Oliver Beckstein <orbeckst@gmail.com>
Maintainer-email: Oliver Beckstein <orbeckst@gmail.com>, Irfan Alibay <ialibay@mdanalysis.org>
License: GNU GENERAL PUBLIC LICENSE
Project-URL: documentation, https://becksteinlab.github.io/propkatraj/
Project-URL: Issue tracker, https://github.com/Becksteinlab/propkatraj/issues
Project-URL: MDAKit registry, https://mdakits.mdanalysis.org/propkatraj.html
Project-URL: source, https://github.com/Becksteinlab/propkatraj
Keywords: molecular simulations
Classifier: Development Status :: 6 - Mature
Classifier: Environment :: Console
Classifier: Intended Audience :: Science/Research
Classifier: License :: OSI Approved :: GNU General Public License v2 or later (GPLv2+)
Classifier: Programming Language :: C
Classifier: Programming Language :: Python
Classifier: Programming Language :: Python :: 3.10
Classifier: Programming Language :: Python :: 3.11
Classifier: Programming Language :: Python :: 3.12
Classifier: Topic :: Scientific/Engineering
Classifier: Topic :: Software Development :: Libraries :: Python Modules
Requires-Python: >=3.10
License-File: LICENSE
Requires-Dist: MDAnalysis >=2.1.0
Requires-Dist: numpy
Requires-Dist: pandas
Requires-Dist: propka ==3.1
Provides-Extra: test
Requires-Dist: pytest >=6.0 ; extra == 'test'
Requires-Dist: pytest-xdist >=2.5 ; extra == 'test'
Requires-Dist: pytest-cov >=3.0 ; extra == 'test'
Requires-Dist: MDAnalysisTests >=2.1.0 ; extra == 'test'
